{
  "collectionName": "components_bloque_alimentos",
  "info": {
    "displayName": "alimento",
    "icon": "bacon",
    "description": ""
  },
  "options": {
    "mainField": "alimento.nombre"
  },
  "attributes": {
    "alimento": {
      "type": "relation",
      "relation": "oneToOne",
      "target": "api::alimento.alimento"
    },
    "cantidad": {
      "type": "integer"
    },
    "unidad": {
      "type": "enumeration",
      "enum": [
        "gramos",
        "onzas",
        "porciones",
        "mililitros",
        "cucharada",
        "unidad"
      ]
    },
    "aclaracion": {
      "type": "string"
    }
  }
}
